sg_module_queues/__init__.py
sg_module_queues/module_queues.py
sg_module_queues/myqueue.py
sg_module_queues/queue.py
sg_module_queues-0.0.3.dist-info/LICENSE
sg_module_queues-0.0.3.dist-info/METADATA
sg_module_queues-0.0.3.dist-info/WHEEL
sg_module_queues-0.0.3.dist-info/top_level.txt
sg_module_queues-0.0.3.dist-info/RECORD
