Metadata-Version: 2.1
Name: sg-module-queues
Version: 0.0.3
Summary: Input, processing and output queues for SG
Home-page: UNKNOWN
Author: Viral Communications
Author-email: viral-grads@media.mit.edu
License: UNKNOWN
Platform: UNKNOWN
Classifier: Programming Language :: Python :: 3
Classifier: License :: OSI Approved :: MIT License
Classifier: Operating System :: OS Independent
